base64mcp/__init__.py
base64mcp/main.py
base64mcp/server.py
mcp_example-0.1.0b0.dist-info/METADATA
mcp_example-0.1.0b0.dist-info/WHEEL
mcp_example-0.1.0b0.dist-info/entry_points.txt
mcp_example-0.1.0b0.dist-info/top_level.txt
mcp_example-0.1.0b0.dist-info/RECORD
