Metadata-Version: 2.4
Name: mcp-example
Version: 0.1.0b0
Summary: 一个使用 FastMCP 实现的 Base64 编码和解码工具。
Author-email: quding <niudear@foxmail.com>
License: MIT
Project-URL: Homepage, https://github.com/yourusername/base64-mcp-tool
Project-URL: Repository, https://github.com/yourusername/base64-mcp-tool
Keywords: base64,mcp,cli,tool
Classifier: Development Status :: 3 - Alpha
Classifier: Intended Audience :: Developers
Classifier: License :: OSI Approved :: MIT License
Classifier: Programming Language :: Python :: 3
Classifier: Programming Language :: Python :: 3.8
Classifier: Programming Language :: Python :: 3.9
Classifier: Programming Language :: Python :: 3.10
Classifier: Programming Language :: Python :: 3.11
Classifier: Programming Language :: Python :: 3.12
Classifier: Topic :: Software Development :: Libraries :: Python Modules
Classifier: Topic :: Utilities
Requires-Python: >=3.13
Requires-Dist: mcp[cli]>=1.9.1
Requires-Dist: wheel>=0.45.1
